poetry_my_first_test/__init__.py
poetry_my_first_test/cli.py
poetry_my_first_test/views/__init__.py
poetry_my_first_test/views/main.py
poetry_my_first_test-1.4.1.dist-info/entry_points.txt
poetry_my_first_test-1.4.1.dist-info/WHEEL
poetry_my_first_test-1.4.1.dist-info/METADATA
poetry_my_first_test-1.4.1.dist-info/RECORD
