Metadata-Version: 2.1
Name: poetry-my-first-test
Version: 1.4.1
Summary: 
Author: puntonim
Author-email: puntonim@gmail.com
Requires-Python: >=3.8,<4.0
Classifier: Programming Language :: Python :: 3
Classifier: Programming Language :: Python :: 3.8
Classifier: Programming Language :: Python :: 3.9
Requires-Dist: click (>=8.0.1,<9.0.0)
Requires-Dist: requests (>=2.25.1,<3.0.0)
